a2a_openai_agents/__init__.py
a2a_openai_agents/a2a_openai_agents.py
a2a_openai_agents/cli.py
a2a_openai_agents/py.typed
a2a_openai_agents-0.0.3.dist-info/METADATA
a2a_openai_agents-0.0.3.dist-info/WHEEL
a2a_openai_agents-0.0.3.dist-info/entry_points.txt
a2a_openai_agents-0.0.3.dist-info/licenses/LICENSE
a2a_openai_agents-0.0.3.dist-info/RECORD
