Metadata-Version: 2.4
Name: a2a-openai-agents
Version: 0.0.3
Summary: Integrates the Agent SDK with A2A
Project-URL: Repository, https://github.com/prassanna-ravishankar/a2a-openai-agents
Author-email: Prassanna Ravishankar <me@prassanna.io>
License-Expression: MIT
License-File: LICENSE
Classifier: Development Status :: 4 - Beta
Classifier: Intended Audience :: Developers
Classifier: Operating System :: OS Independent
Classifier: Programming Language :: Python
Classifier: Programming Language :: Python :: 3
Classifier: Programming Language :: Python :: 3.11
Classifier: Programming Language :: Python :: 3.12
Classifier: Programming Language :: Python :: 3.13
Classifier: Typing :: Typed
Requires-Python: <4.0,>=3.11
Requires-Dist: a2a-sdk>=0.1.0
Requires-Dist: fastapi>=0.104.0
Requires-Dist: openai-agents>=0.0.13
Requires-Dist: temporalio>=1.6.0
Requires-Dist: uvicorn>=0.24.0
